{"tag":{"label":"transparent","permalink":"/docs/tags/transparent","allTagsPath":"/docs/tags","count":2,"items":[{"id":"getting-started/shielded-vs-transparent","title":"Shielded vs Transparent","description":"Understanding the difference between shielded and transparent transactions in Namada","permalink":"/docs/getting-started/shielded-vs-transparent"},{"id":"guides/transactions/unshield-assets","title":"Unshield Assets","description":"How to unshield assets from the MASP back to transparent addresses","permalink":"/docs/guides/transactions/unshield-assets"}],"unlisted":false}}